Workbook

Sheet 损益表
A1: 损益表 (Income Statement)
A2: 项目 | B2: 2022 | C2: 2023 | D2: 2024 | E2: 2025E | F2: 2026E
A3: 营业收入 | B3: 50000 | C3: 60000 | D3: 72000
A4: 营业成本 | B4: 30000 | C4: 35000 | D4: 40000
A5: 毛利 | B5: =B3-B4 | C5: =C3-C4 | D5: =D3-D4 | E5: =E3-E4 | F5: =F3-F4
A6: 销售费用 | B6: 5000 | C6: 6000 | D6: 7200
A7: 管理费用 | B7: 3000 | C7: 3500 | D7: 4000
A8: 研发费用 | B8: 2000 | C8: 2500 | D8: 3000
A9: 营业利润 | B9: =B5-B6-B7-B8 | C9: =C5-C6-C7-C8 | D9: =D5-D6-D7-D8 | E9: =E5-E6-E7-E8 | F9: =F5-F6-F7-F8
A10: 财务费用 | B10: 500 | C10: 600 | D10: 700
A11: 税前利润 | B11: =B9-B10 | C11: =C9-C10 | D11: =D9-D10 | E11: =E9-E10 | F11: =F9-F10
A12: 所得税 | B12: =B11*0.25 | C12: =C11*0.25 | D12: =D11*0.25 | E12: =E11*0.25 | F12: =F11*0.25
A13: 净利润 | B13: =B11-B12 | C13: =C11-C12 | D13: =D11-D12 | E13: =E11-E12 | F13: =F11-F12

Sheet 资产负债表
A1: 资产负债表 (Balance Sheet)
A2: 项目 | B2: 2022 | C2: 2023 | D2: 2024 | E2: 2025E | F2: 2026E
A3: 资产
A4: 流动资产 | B4: 25000 | C4: 30000 | D4: 36000
A5: 现金及等价物 | B5: 10000 | C5: 12000 | D5: 15000
A6: 应收账款 | B6: 8000 | C6: 10000 | D6: 12000
A7: 存货 | B7: 7000 | C7: 8000 | D7: 9000
A8: 非流动资产 | B8: 45000 | C8: 50000 | D8: 54000
A9: 固定资产净值 | B9: 35000 | C9: 38000 | D9: 40000
A10: 无形资产 | B10: 10000 | C10: 12000 | D10: 14000
A11: 总资产 | B11: =B4+B9 | C11: =C4+C9 | D11: =D4+D9 | E11: =E4+E9 | F11: =F4+F9
A13: 负债与权益
A14: 流动负债 | B14: 15000 | C14: 18000 | D14: 20000
A15: 应付账款 | B15: 8000 | C15: 9000 | D15: 10000
A16: 短期借款 | B16: 7000 | C16: 9000 | D16: 10000
A17: 非流动负债 | B17: 20000 | C17: 22000 | D17: 25000
A18: 长期借款 | B18: 20000 | C18: 22000 | D18: 25000
A19: 总负债 | B19: =B14+B17 | C19: =C14+C17 | D19: =D14+D17 | E19: =E14+E17 | F19: =F14+F17
A20: 股东权益 | B20: =B21+B22 | C20: =C21+C22 | D20: =D21+D22 | E20: =E21+E22 | F20: =F21+F22
A21: 实收资本 | B21: 20000 | C21: 20000 | D21: 20000
A22: 留存收益 | B22: 15000 | C22: =B22+损益表!B13 | D22: =C22+损益表!C13 | E22: =D22+损益表!D13 | F22: =E22+损益表!E13
A23: 负债与权益总计 | B23: =B19+B20 | C23: =C19+C20 | D23: =D19+D20 | E23: =E19+E20 | F23: =F19+F20

Sheet 现金流量表
A1: 现金流量表 (Cash Flow Statement)
A2: 项目 | B2: 2022 | C2: 2023 | D2: 2024 | E2: 2025E | F2: 2026E
A3: 经营活动现金流
A4: 净利润 | B4: =损益表!B13 | C4: =损益表!C13 | D4: =损益表!D13 | E4: =损益表!E13 | F4: =损益表!F13
A5: 折旧摊销 | B5: 3000 | C5: 3500 | D5: 4000
A6: 应收账款变动 | B6: 0 | C6: =资产负债表!B6-资产负债表!C6 | D6: =资产负债表!C6-资产负债表!D6 | E6: =资产负债表!D6-资产负债表!E6 | F6: =资产负债表!E6-资产负债表!F6
A7: 存货变动 | B7: 0 | C7: =资产负债表!B7-资产负债表!C7 | D7: =资产负债表!C7-资产负债表!D7 | E7: =资产负债表!D7-资产负债表!E7 | F7: =资产负债表!E7-资产负债表!F7
A8: 应付账款变动 | B8: 0 | C8: =资产负债表!C15-资产负债表!B15 | D8: =资产负债表!D15-资产负债表!C15 | E8: =资产负债表!E15-资产负债表!D15 | F8: =资产负债表!F15-资产负债表!E15
A9: 经营活动现金流净额 | B9: =B4+B5+B6+B7+B8 | C9: =C4+C5+C6+C7+C8 | D9: =D4+D5+D6+D7+D8 | E9: =E4+E5+E6+E7+E8 | F9: =F4+F5+F6+F7+F8
A11: 投资活动现金流
A12: 资本支出 | B12: -5000 | C12: -6000 | D12: -6000
A13: 投资活动现金流净额 | B13: =B12 | C13: =C12 | D13: =D12 | E13: =E12 | F13: =F12
A15: 筹资活动现金流
A16: 借款增加 | B16: 2000 | C16: 4000 | D16: 4000
A17: 筹资活动现金流净额 | B17: =B16 | C17: =C16 | D17: =D16 | E17: =E16 | F17: =F16
A19: 现金净增加额 | B19: =B9+B13+B17 | C19: =C9+C13+C17 | D19: =D9+D13+D17 | E19: =E9+E13+E17 | F19: =F9+F13+F17
A20: 期初现金 | B20: =资产负债表!B5 | C20: =B21 | D20: =C21 | E20: =D21 | F20: =E21
A21: 期末现金 | B21: =B20+B19 | C21: =C20+C19 | D21: =D20+D19 | E21: =E20+E19 | F21: =F20+F19
